spellgen-0.3.0.dist-info/METADATA
spellgen-0.3.0.dist-info/WHEEL
spellgen/__init__.py
spellgen/__init__.pyi
spellgen/py.typed
spellgen/spellgen.abi3.so
spellgen-0.3.0.dist-info/RECORD
