Metadata-Version: 2.4
Name: spellgen
Version: 0.3.0
Classifier: Development Status :: 4 - Beta
Classifier: Intended Audience :: Developers
Classifier: License :: OSI Approved :: MIT License
Classifier: Programming Language :: Python :: 3
Classifier: Programming Language :: Python :: 3.8
Classifier: Programming Language :: Python :: 3.9
Classifier: Programming Language :: Python :: 3.10
Classifier: Programming Language :: Python :: 3.11
Classifier: Programming Language :: Python :: 3.12
Classifier: Programming Language :: Rust
Classifier: Topic :: Games/Entertainment
Classifier: Topic :: Multimedia :: Graphics
Summary: A library for creating spell card images for the game Wizard101
Keywords: wizard101,gaming,image-generation,cards
Author-email: Spiral404 <noreply@spiral404.com>
License: MIT
Requires-Python: >=3.8
